ov_aes_cipher/__init__.py
ov_aes_cipher/ov_aes_cipher.py
ov_aes_cipher-1.1.3.dist-info/.gitignore
ov_aes_cipher-1.1.3.dist-info/METADATA
ov_aes_cipher-1.1.3.dist-info/WHEEL
ov_aes_cipher-1.1.3.dist-info/top_level.txt
ov_aes_cipher-1.1.3.dist-info/RECORD
